mpi_sppy-0.13.1.dist-info/licenses/LICENSE.md
mpisppy/MPI.py
mpisppy/__init__.py
mpisppy/generic_cylinders.py
mpisppy/log.py
mpisppy/phbase.py
mpisppy/scenario_tree.py
mpisppy/spbase.py
mpisppy/spin_the_wheel.py
mpisppy/spopt.py
mpisppy/agnostic/__init__.py
mpisppy/agnostic/agnostic.py
mpisppy/agnostic/agnostic_cylinders.py
mpisppy/agnostic/ampl_guest.py
mpisppy/agnostic/farmer4agnostic.py
mpisppy/agnostic/gams_guest.py
mpisppy/agnostic/pyomo_guest.py
mpisppy/agnostic/examples/__init__.py
mpisppy/agnostic/examples/afew_agnostic.py
mpisppy/agnostic/examples/executing_single_gms_file.py
mpisppy/agnostic/examples/farmer.py
mpisppy/agnostic/examples/farmer_ampl_model.py
mpisppy/agnostic/examples/farmer_gams_model.py
mpisppy/agnostic/examples/farmer_gurobipy_model.py
mpisppy/agnostic/examples/steel_ampl_model.py
mpisppy/agnostic/examples/transport_gams_model.py
mpisppy/confidence_intervals/__init__.py
mpisppy/confidence_intervals/ciutils.py
mpisppy/confidence_intervals/confidence_config.py
mpisppy/confidence_intervals/mmw_ci.py
mpisppy/confidence_intervals/mmw_conf.py
mpisppy/confidence_intervals/multi_seqsampling.py
mpisppy/confidence_intervals/sample_tree.py
mpisppy/confidence_intervals/seqsampling.py
mpisppy/confidence_intervals/zhat4xhat.py
mpisppy/convergers/__init__.py
mpisppy/convergers/converger.py
mpisppy/convergers/fracintsnotconv.py
mpisppy/convergers/norm_rho_converger.py
mpisppy/convergers/norms_and_residuals.py
mpisppy/convergers/primal_dual_converger.py
mpisppy/cylinders/__init__.py
mpisppy/cylinders/cross_scen_spoke.py
mpisppy/cylinders/fwph_spoke.py
mpisppy/cylinders/hub.py
mpisppy/cylinders/lagranger_bounder.py
mpisppy/cylinders/lagrangian_bounder.py
mpisppy/cylinders/lshaped_bounder.py
mpisppy/cylinders/ph_dual_spoke.py
mpisppy/cylinders/ph_ob.py
mpisppy/cylinders/reduced_costs_spoke.py
mpisppy/cylinders/relaxed_ph_spoke.py
mpisppy/cylinders/slam_heuristic.py
mpisppy/cylinders/spcommunicator.py
mpisppy/cylinders/spoke.py
mpisppy/cylinders/spwindow.py
mpisppy/cylinders/subgradient_bounder.py
mpi_sppy-0.13.1.dist-info/METADATA
mpi_sppy-0.13.1.dist-info/WHEEL
mpi_sppy-0.13.1.dist-info/top_level.txt
mpi_sppy-0.13.1.dist-info/RECORD
