Metadata-Version: 2.4
Name: mpi-sppy
Version: 0.13.1
Summary: mpi-sppy
Home-page: https://github.com/Pyomo/mpi-sppy
Author: David Woodruff
Author-email: David Woodruff <dlwoodruff@ucdavis.edu>
License: License
Project-URL: homepage, https://github.com/Pyomo/mpi-sppy
Project-URL: source, https://github.com/Pyomo/mpi-sppy
Project-URL: download, https://github.com/Pyomo/mpi-sppy
Project-URL: documentation, https://mpi-sppy.readthedocs.io
Project-URL: tracker, https://github.com/Pyomo/mpi-sppy/issues
Requires-Python: >=3.9
License-File: LICENSE.md
Requires-Dist: numpy<2
Requires-Dist: scipy
Requires-Dist: pandas
Requires-Dist: sortedcollections
Requires-Dist: pyomo>=6.4
Provides-Extra: doc
Requires-Dist: sphinx_rtd_theme; extra == "doc"
Requires-Dist: sphinx; extra == "doc"
Provides-Extra: mpi
Requires-Dist: mpi4py>=3.0.3; extra == "mpi"
Dynamic: author
Dynamic: home-page
Dynamic: license-file
Dynamic: requires-python
